[
  {
    "name": "MILITARYTODAYIR",
    "title": "(تحلیل نظامی و اخبار جنگ) MilitaryToday.IR",
    "username": "MILITARYTODAYIR",
    "participantsCount": 15794,
    "profilePhoto": "profile.jpg",
    "lastUpdated": "2026-05-11T21:01:34.544Z",
    "lastMessage": {
      "id": 47231,
      "date": "2026-05-11T20:56:31.000Z",
      "media": "media_47231.jpg",
      "caption": "⚠️🇮🇷🇵🇰🇺🇸- مقامات آمریکایی به شبکه CBS نیوز گفتند که در حالی که پاکستان به طور علنی به عنوان کانال دیپلماتیک بین ایران و ایالات متحده آمریکا عمل کرده اما به طور مخفیانه اجازه داده است هواپیماهای نظامی ایران در پایگاه نیروی هوایی پاکستان در نور خان نزدیک راولپندی مستقر شوند که آن‌ها را از حملات آمریکا محافظت کند.\n\n⚠️مقامات گفتند: ایران چندین هواپیما را بلافاصله پس از اعلام آتش‌بس توسط رئیس‌جمهور ترامپ در اوایل آوریل به آنجا منتقل کرده از جمله یک هواپیمای شناسایی RC-130 نیروی هوایی ارتش جمهوری اسلامی ایران.\n\n⚠️یک مسئول هوانوردی غیرنظامی افغانستان به CBS گفت که همچنین یک هواپیمای مسافربری شرکت ماهان ایر ایران در فرودگاه کابل، پایتخت افغانستان پارک شده است.\n\n⚠️یک مقام ارشد پاکستانی ادعاهای مربوط به پایگاه هوایی نور خان را رد کرد و به CBS نیوز گفت که «پایگاه نور خان درست در قلب شهر است؛ یک ناوگان بزرگ هواپیما که در آنجا پارک شده باشد نمی‌تواند از دید عموم پنهان بماند.»\n\nLancer ✍\n\n@MilitaryTodayIR"
    }
  },
  {
    "name": "persian_trend_official",
    "title": "کانال رسمی پرشین ترند",
    "username": "persian_trend_official",
    "participantsCount": 65240,
    "profilePhoto": "profile.jpg",
    "lastUpdated": "2026-05-11T21:01:36.265Z",
    "lastMessage": {
      "id": 13949,
      "date": "2026-05-11T20:39:01.000Z",
      "media": "media_13949.jpg",
      "caption": "🔹محمد باقر قالیباف \n\n**💢هیچ راهی جز پذیرش حقوق ملت ایران، آن‌گونه که در طرح ۱۴ بندی آمده، وجود ندارد. \n\n💢هر مسیر دیگری کاملاً بی‌نتیجه خواهد بود و چیزی جز شکست‌های پیاپی به همراه نخواهد داشت. \n\n💢هرچه بیشتر وقت‌کشی کنند، هزینه بیشتری هم از جیب مالیات‌دهندگان آمریکایی پرداخت خواهد شد.\n**\n\n**🫆:**`Tony`\n\n**📌 ****@persian_trend_official****\nپرشین ترند | متفاوت‌ترین کانال نظامی**"
    }
  },
  {
    "name": "TweetyChannel",
    "title": "توییتی",
    "username": "TweetyChannel",
    "participantsCount": 728268,
    "profilePhoto": "profile.jpg",
    "lastUpdated": "2026-05-11T21:01:37.269Z",
    "lastMessage": {
      "id": 380110,
      "date": "2026-05-11T21:01:01.000Z",
      "media": "media_380110.jpg",
      "caption": "✨ **BARBARA VPN** ✨\n** ** \n🔴**سرور اختصاصی با پایداری بالا و‌ بدون قطعی**\nبا تضمین بازگشت وجه ⏩\n💠 **BRBARA BOT**"
    }
  },
  {
    "name": "chavoshin",
    "title": "کانال خبری چاوشین",
    "username": "chavoshin",
    "participantsCount": 938,
    "profilePhoto": "profile.jpg",
    "lastUpdated": "2026-05-11T21:01:38.643Z",
    "lastMessage": {
      "id": 19686,
      "date": "2026-05-11T18:31:08.000Z",
      "text": "ترامپ: آتش‌بس با رژیم ایران به‌شدت شکننده است؛ با گروهی «دیوانه» سروکار داریم\n\n#چاوشین \n\n@chavoshin"
    }
  },
  {
    "name": "jangaavaran1390",
    "title": "جنگاوران",
    "username": "jangaavaran1390",
    "participantsCount": 137210,
    "profilePhoto": "profile.jpg",
    "lastUpdated": "2026-05-11T21:01:39.146Z",
    "lastMessage": {
      "id": 131027,
      "date": "2026-05-11T20:29:02.000Z",
      "text": "خبر خوب رفقا ؛ سرویس وی آی پی شارژ شد  ؛ سرویس [💎VIP] با اتصال پایدار در سخت‌ترین شرایط !\n\n⚠️ تمام کانفیگ ها تست شده توی سخت  ترین شرایط فیلترینگ!! \n\nبرای اولین بار در کل تلگرام سرویس اپن وی پی ان موجود کردیم با حجم نامحدود کاملا ضمانتی !!!\n\nهمچنین سرویس v2rayNG و v2box هم داریم به صورت حجمی با کمترین قیمت \n\nاز الان میتونید با 50% تخفیف میتونید از آیدی زیر تهیه کنید | بصورت موقت تخفیف گذاشتیم !\n\n✅ پیشنهاد میشه قبل از بسته شدن ظرفیت از آیدی زیر  مجموعه اشتراک VIP تهیه کنید :\n\n@Majidalizadeh22"
    }
  },
  {
    "name": "putakk",
    "title": "PooriaPutaK",
    "username": "putakk",
    "participantsCount": 227705,
    "profilePhoto": "profile.jpg",
    "lastUpdated": "2026-05-11T21:01:39.661Z",
    "lastMessage": {
      "id": 25493,
      "date": "2026-05-11T19:46:48.000Z",
      "text": "🔴قالیباف:\nنیروهای مسلح ما آمادهٔ پاسخگویی درس‌آموز به هر تجاوزی هستن.\nاستراتژی اشتباه و تصمیم‌های اشتباه، همیشه نتیجهٔ اشتباه خواهد داشت، همهٔ دنیا قبلاً اینو فهمیدن. \nما برای تمام گزینه‌ها آماده هستیم؛ شگفت‌زده خواهند شد."
    }
  },
  {
    "name": "pouriazeraati",
    "title": "پوریا زراعتی Pouria Zeraati",
    "username": "pouriazeraati",
    "participantsCount": 111785,
    "profilePhoto": "profile.jpg",
    "lastUpdated": "2026-05-11T21:01:40.215Z",
    "lastMessage": {
      "id": 743,
      "date": "2026-05-11T00:14:28.000Z",
      "media": "media_743.mp4",
      "caption": "دقیق در جریانه :))\n\n'فارسی بلد نیستم اما [در ایران] صدام می‌کنن «بی‌بی جون».'\n\n@pouriazeraati"
    }
  },
  {
    "name": "VahidOnline",
    "title": "Vahid Online وحید آنلاین",
    "username": "VahidOnline",
    "participantsCount": 1340980,
    "profilePhoto": "profile.jpg",
    "lastUpdated": "2026-05-11T21:01:40.735Z",
    "lastMessage": {
      "id": 75426,
      "date": "2026-05-11T20:28:53.000Z",
      "media": "media_75426.jpg",
      "caption": "وزارت خزانه‌داری ایالات متحده، روز دوشنبه، ۲۱ اردیبهشت‌ماه، در بیانیه‌ای رسمی اعلام کرد که پاسخ اخیر تهران به پیشنهاد دیپلماتیک واشنگتن، نه‌تنها از نظر سیاسی غیرقابل‌قبول است، بلکه با استانداردهای لازم برای لغو تحریم‌های مالی و اقتصادی نیز همخوانی ندارد.\n\n این وزارتخانه تاکید کرد که رویکرد فعلی ایران مانع از هرگونه گشایش در مسیر مبادلات بین‌المللی و آزادسازی دارایی‌های بلوکه شده می‌شود و تا زمانی که تعهدات شفافی در حوزه برنامه هسته‌ای ارائه نشود، فشارها بر شبکه مالی این کشور ادامه خواهد یافت.\n\nدر همین راستا، اسکات بسنت، وزیر خزانه‌داری دولت دونالد ترامپ، در اکس با بازنشر این بیانیه، موضعی قاطعانه اتخاذ کرد. \nاو با اشاره به اینکه پاسخ تهران نشان‌دهنده عدم تمایل این کشور به همکاری واقعی است، نوشت: «در حالی که دولت ترامپ با حسن نیت مسیری برای دیپلماسی باز کرد، تهران با پاسخی کاملا غیرقابل‌قبول به میز مذاکره بازگشته است.» بسنت تاکید کرد که وزارت خزانه‌داری، سیاست‌های مالی را به گونه‌ای تنظیم خواهد کرد که جمهوری اسلامی متوجه شود عدم پذیرش توافق، هزینه‌های اقتصادی سنگین و غیرقابل‌جبرانی برای نظام پولی و بانکی این کشور به همراه خواهد داشت. او نوشت: «زمان آن رسیده که تهران متوجه شود هزینه لجاجت، فروپاشی کامل اقتصادی است».\n@VahidOOnLine\n\n📡 @VahidOnline"
    }
  },
  {
    "name": "MatinSenPaii",
    "title": "Matin SenPai",
    "username": "MatinSenPaii",
    "participantsCount": 93918,
    "profilePhoto": "profile.jpg",
    "lastUpdated": "2026-05-11T21:01:41.250Z",
    "lastMessage": {
      "id": 3012,
      "date": "2026-05-11T20:06:55.000Z",
      "media": "media_3012.jpg",
      "caption": "به زودی یه آموزش بر پایه‌ی DNS داریم. یک دونه رایگان بدون سرور، یکی با سرور.\nبه همراه آموزش پیدا کردن ریزالور\nبا تشکر از بچه‌های تیممون، WhiteDNS\n(توی این عکس با سرور رایگان وصلم)"
    }
  },
  {
    "name": "IranintlTV",
    "title": "Iran International ایران اینترنشنال",
    "username": "IranintlTV",
    "participantsCount": 1321254,
    "profilePhoto": "profile.jpg",
    "lastUpdated": "2026-05-11T21:01:41.756Z",
    "lastMessage": {
      "id": 336709,
      "date": "2026-05-11T20:47:49.000Z",
      "media": "media_336709.jpg",
      "caption": "مجتبی ذوالنوری، عضو کمیسیون حقوقی مجلس، گفت: «لازم نیست در تنگه هرمز باشیم تا هر شناوری را که از آنجا رد می‌شود، بزنیم. از سمنان و مشهد و تهران می‌زنیم. چند شناور که آنجا غرق شود، خود تنگه بسته می‌شود. روی بحث مین‌ریزی کار کردیم و نجابت به خرج دادیم از این حق استفاده نکردیم.»\nhttps://iranintl.com/202605116088"
    }
  },
  {
    "name": "netblocks",
    "title": "NetBlocks",
    "username": "netblocks",
    "participantsCount": 41548,
    "profilePhoto": "profile.jpg",
    "lastUpdated": "2026-05-11T21:01:42.902Z",
    "lastMessage": {
      "id": 1485,
      "date": "2026-05-11T19:56:49.000Z",
      "media": "media_1485.jpg",
      "caption": "⛈️ Confirmed: Metrics show declines in internet connectivity in South Africa with high impact to the Western Cape, corresponding to reports of power outages as authorities declare a national disaster amid flooding, heavy winds and snowfall"
    }
  },
  {
    "name": "ircfspace",
    "title": "IRCF | اینترنت آزاد برای همه",
    "username": "ircfspace",
    "participantsCount": 93008,
    "profilePhoto": "profile.jpg",
    "lastUpdated": "2026-05-11T21:01:43.519Z",
    "lastMessage": {
      "id": 2311,
      "date": "2026-05-11T18:03:17.000Z",
      "media": "media_2311.jpg",
      "caption": "#پیامرسان_بومی\n\n🔗 ᴡᴇʙꜱɪᴛᴇ • ᴠᴘɴʜᴜʙ • ɢɪᴛʜᴜʙᴍɪʀʀᴏʀ\n@ircfspace"
    }
  },
  {
    "name": "TechTube",
    "title": "TechTube 𝕏 تک توب",
    "username": "TechTube",
    "participantsCount": 76802,
    "profilePhoto": "profile.jpg",
    "lastUpdated": "2026-05-11T21:01:44.048Z",
    "lastMessage": {
      "id": 17156,
      "date": "2026-05-11T20:01:57.000Z",
      "media": "media_17156.mp4",
      "caption": "اولین تراکنش ازمایشی با استفاده از شبکه پرداخت بین المللی ویزا و مسترکارت بعد از 15 سال در سوریه\n\nبا اتصال این شبکه ها هم شهروندان سوریه میتونن از کارتهای خودشون در این شبکه های پرداخت استفاده کنن و هم گردشگران خارجی در هنگام سفر به سوریه امکان استفاه از کارتهای بانکی بین المللی رو خواهند داشت. \n\nویزا و مسترکارت در سال 2011 به دنباله روی از تحریمهای مالی وزارت خزانه داری امریکا از سوریه خارج شدن ولی کمتر از یک سال پیش، وزارت خزانه داری این تحریمارو برداشت که راه رو برای فعالیت دوباره این شبکه ها باز کرد. \n\n🔎 enabbaladi \n\n📍 @TechTube"
    }
  },
  {
    "name": "factnameh",
    "title": "FactNameh | فکت‌نامه",
    "username": "factnameh",
    "participantsCount": 113346,
    "profilePhoto": "profile.jpg",
    "lastUpdated": "2026-05-11T21:01:44.612Z",
    "lastMessage": {
      "id": 5592,
      "date": "2026-05-11T20:16:13.000Z",
      "media": "media_5592.jpg",
      "caption": "❌ **ادعای نادرست اخراج سربازان آمریکایی از پایگاه شاهزاده سلطان عربستان**\n\n🔹در شبکه‌های اجتماعی ادعا شده که عربستان سعودی نیروهای آمریکایی را از پایگاه پرنس سلطان اخراج کرده است.\n\n🔹این ادعا نادرست است و هیچ گزارشی درباره اخراج نیروهای آمریکایی از عربستان منتشر نشده است.\n\n🔹تصاویری که در این ادعا به عنوان پایگاه پرنس سلطان منتشر شده، ساخته هوش مصنوعی است.\n\n🔹گزارش خبرگزاری‌های معتبر، از مخالفت عربستان سعودی با عملیات نظامی آمریکا در تنگه هرمز خبر می‌دهند.\n\n🔹گاردین، وال‌استریت‌ژورنال و ان‌بی‌سی گفته‌اند عربستان به آمریکا اجازه نداده در عملیاتی به نام «پروژه آزادی» از حریم هوایی و پایگاه‌های آمریکا در این کشور استفاده کند.\n\n🔹«پروژه آزادی» در تنگه هرمز لغو شد و وال‌استریت ژورنال از رفع محدودیت‌های آمریکا در استفاده از حریم هوایی این کشور خبر داد.\n\n🔹بنابراین فکت‌نامه به ادعای اخراج نیروهای آمریکایی از پایگاه پرنس سلطان نشان **«نادرست»** می‌دهد.\n\n👈 در فکت‌نامه بخوانید\n\n🌐 @Factnameh"
    }
  },
  {
    "name": "MoradVaisiPodcasts",
    "title": "پادکست‌های روزانه مراد ویسی",
    "username": "MoradVaisiPodcasts",
    "participantsCount": 96,
    "profilePhoto": "profile.jpg",
    "lastUpdated": "2026-05-11T21:01:45.166Z",
    "lastMessage": {
      "id": 869,
      "date": "2026-05-08T18:59:40.000Z",
      "media": "media_869.ogg",
      "caption": "خواندن اسامی هزار جاویدنام دیگر\n\n🎙️ تلگرام پادکست‌های روزانه\n🚀 بوست کانال تلگرام\n📺 یوتیوب مراد ویسی\n📺 یوتیوب سیاست با مراد ویسی\n📺 یوتیوب تاریخ سیاه\n✍️ اکس مراد ویسی (توییتر سابق)\n📸 اینستاگرام مراد ویسی\n✍️ مقالات مراد ویسی\n\n#مراد_ویسی #Morad_Vaisi"
    }
  },
  {
    "name": "OfficialRezaPahlavi",
    "title": "Reza Pahlavi | رضا پهلوی",
    "username": "OfficialRezaPahlavi",
    "participantsCount": 354551,
    "profilePhoto": "profile.jpg",
    "lastUpdated": "2026-05-11T21:01:45.654Z",
    "lastMessage": {
      "id": 1832,
      "date": "2026-05-01T17:11:24.000Z",
      "media": "media_1832.jpg"
    }
  },
  {
    "name": "mitivpn",
    "title": "اینترنت آزاد",
    "username": "mitivpn",
    "participantsCount": 2434427,
    "profilePhoto": "profile.jpg",
    "lastUpdated": "2026-05-11T21:01:46.230Z",
    "lastMessage": {
      "id": 16834,
      "date": "2026-05-11T11:53:19.000Z",
      "media": "media_16834.npvt",
      "caption": "🌐 **فقط روی شاتل خونگی و شاتل موبایل  وصل میشه**\n\n**اینترنت آزاد برای همه, یا هیچکس **🖤**\n\n**T.me/MiTiVPN** **🥇"
    }
  }
]